jsonfind/__init__.py
jsonfind/_cli.py
jsonfind/_version.py
jsonfind/jsonfind.py
jsonfind-0.1.2.dist-info/LICENSE
jsonfind-0.1.2.dist-info/METADATA
jsonfind-0.1.2.dist-info/WHEEL
jsonfind-0.1.2.dist-info/entry_points.txt
jsonfind-0.1.2.dist-info/top_level.txt
jsonfind-0.1.2.dist-info/RECORD
