Metadata-Version: 2.1
Name: jsonfind
Version: 0.1.2
Summary: search dict
Home-page: https://github.com/wtnb75/jsonfind
Author: Takashi WATANABE
Author-email: wtnb75@gmail.com
License: MIT
Platform: UNKNOWN
Classifier: Development Status :: 3 - Alpha
Classifier: Intended Audience :: Developers
Classifier: License :: OSI Approved :: MIT License
Classifier: Programming Language :: Python :: 3
Requires-Dist: Click
Requires-Dist: jsonpath
Requires-Dist: jsonpointer
Provides-Extra: dev
Requires-Dist: dirimport ; extra == 'dev'
Requires-Dist: nose ; extra == 'dev'
Requires-Dist: coverage ; extra == 'dev'
Requires-Dist: wheel ; extra == 'dev'
Requires-Dist: twine ; extra == 'dev'
Requires-Dist: pip2pi ; extra == 'dev'
